gemini_webapi/__init__.py
gemini_webapi/client.py
gemini_webapi/constants.py
gemini_webapi/exceptions.py
gemini_webapi/components/__init__.py
gemini_webapi/components/gem_mixin.py
gemini_webapi/types/__init__.py
gemini_webapi/types/candidate.py
gemini_webapi/types/gem.py
gemini_webapi/types/grpc.py
gemini_webapi/types/image.py
gemini_webapi/types/modeloutput.py
gemini_webapi/utils/__init__.py
gemini_webapi/utils/decorators.py
gemini_webapi/utils/get_access_token.py
gemini_webapi/utils/load_browser_cookies.py
gemini_webapi/utils/logger.py
gemini_webapi/utils/rotate_1psidts.py
gemini_webapi/utils/upload_file.py
gemini_webapi-1.16.0.dist-info/licenses/LICENSE
gemini_webapi-1.16.0.dist-info/METADATA
gemini_webapi-1.16.0.dist-info/WHEEL
gemini_webapi-1.16.0.dist-info/top_level.txt
gemini_webapi-1.16.0.dist-info/RECORD
