Metadata-Version: 2.4
Name: gemini-webapi
Version: 1.16.0
Summary: ✨ An elegant async Python wrapper for Google Gemini web app
Author: UZQueen
License:                     GNU AFFERO GENERAL PUBLIC LICENSE
Project-URL: Repository, https://github.com/HanaokaYuzu/Gemini-API
Project-URL: Issues, https://github.com/HanaokaYuzu/Gemini-API/issues
Keywords: API,async,Gemini,Bard,Google,Generative AI,LLM
Classifier: Development Status :: 4 - Beta
Classifier: Intended Audience :: Developers
Classifier: Programming Language :: Python :: 3
Classifier: Programming Language :: Python :: 3.11
Classifier: Programming Language :: Python :: 3.12
Requires-Python: >=3.10
License-File: LICENSE
Requires-Dist: httpx[http2]~=0.28.1
Requires-Dist: loguru~=0.7.3
Requires-Dist: orjson~=3.11.1
Requires-Dist: pydantic~=2.12.2
Dynamic: license-file
